rpdk/java/__init__.py
rpdk/java/codegen.py
rpdk/java/resolver.py
rpdk/java/utils.py
rpdk/java/data/java.gitignore
rpdk/java/data/jsonSchemas.xml
rpdk/java/data/log4j2.xml
rpdk/java/data/build-image-src/Dockerfile-java11
rpdk/java/data/build-image-src/Dockerfile-java17
rpdk/java/templates/generate/BaseConfiguration.java
rpdk/java/templates/generate/BaseHandler.java
rpdk/java/templates/generate/HandlerWrapper.java
rpdk/java/templates/generate/POJO.java
rpdk/java/templates/generate/ResourceModel.java
rpdk/java/templates/generate/hook/BaseHookConfiguration.java
rpdk/java/templates/generate/hook/BaseHookHandler.java
rpdk/java/templates/generate/hook/HookHandlerWrapper.java
rpdk/java/templates/generate/hook/HookInputModel.java
rpdk/java/templates/generate/hook/ResourceHookTarget.java
rpdk/java/templates/generate/hook/ResourceHookTargetModel.java
rpdk/java/templates/init/default/StubHandler.java
rpdk/java/templates/init/default/StubHandlerTest.java
rpdk/java/templates/init/default/StubHookHandler.java
rpdk/java/templates/init/default/StubHookHandlerTest.java
rpdk/java/templates/init/default/StubListHandler.java
rpdk/java/templates/init/default/StubListHandlerTest.java
rpdk/java/templates/init/guided_aws/AbstractTestBase.java
rpdk/java/templates/init/guided_aws/BaseHandlerStd.java
rpdk/java/templates/init/guided_aws/BaseHookHandlerStd.java
rpdk/java/templates/init/guided_aws/ClientBuilder.java
rpdk/java/templates/init/guided_aws/HookTranslator.java
rpdk/java/templates/init/guided_aws/ResourceModel.java
rpdk/java/templates/init/guided_aws/StubCreateHandler.java
rpdk/java/templates/init/guided_aws/StubDeleteHandler.java
rpdk/java/templates/init/guided_aws/StubHandlerTest.java
rpdk/java/templates/init/guided_aws/StubListHandler.java
rpdk/java/templates/init/guided_aws/StubListHandlerTest.java
rpdk/java/templates/init/guided_aws/StubPreCreateHookHandler.java
rpdk/java/templates/init/guided_aws/StubPreCreateHookHandlerTest.java
cloudformation_cli_java_plugin-2.2.3.dist-info/LICENSE
cloudformation_cli_java_plugin-2.2.3.dist-info/METADATA
cloudformation_cli_java_plugin-2.2.3.dist-info/WHEEL
cloudformation_cli_java_plugin-2.2.3.dist-info/entry_points.txt
cloudformation_cli_java_plugin-2.2.3.dist-info/top_level.txt
cloudformation_cli_java_plugin-2.2.3.dist-info/zip-safe
cloudformation_cli_java_plugin-2.2.3.dist-info/RECORD
